bytedance_offline_ra_solver/__init__.py
bytedance_offline_ra_solver-0.0.1.dist-info/METADATA
bytedance_offline_ra_solver-0.0.1.dist-info/WHEEL
bytedance_offline_ra_solver-0.0.1.dist-info/top_level.txt
bytedance_offline_ra_solver-0.0.1.dist-info/RECORD
