Metadata-Version: 2.1
Name: bytedance-offline-ra-solver
Version: 0.0.1
Summary: A simple package named bytedance_offline_ra_solver
Home-page: https://github.com/artifact/bytedance_offline_ra_solver.git
Author: artifact
Author-email: artifact@example.com
License: UNKNOWN
Platform: UNKNOWN
Classifier: Programming Language :: Python :: 3
Classifier: License :: OSI Approved :: MIT License
Classifier: Operating System :: OS Independent
